{
  "locker_open": {
    "subtitle": "sounds.scpff.locker_open",
    "sounds": [
      "scpff:locker_open"
    ]
  },
  "locker_close": {
    "subtitle": "sounds.scpff.locker_close",
    "sounds": [
      "scpff:locker_close"
    ]
  },
  "scp058beating": {
    "subtitle": "sounds.scpff.scp058beating",
    "sounds": [
      "scpff:scp058beating"
    ]
  },
  "scp131ambient": {
    "sounds": [
      "scpff:scp131/scp131_1",
      "scpff:scp131/scp131_2",
      "scpff:scp131/scp131_3",
      "scpff:scp131/scp131_4",
      "scpff:scp131/scp131_5",
      "scpff:scp131/scp131_6"
    ],
    "subtitle": "sounds.scpff.scp131ambient"
  },
  "scp131hurt": {
    "sounds": [
      "scpff:scp131/scp131hurt"
    ],
    "subtitle": "sounds.scpff.scp131hurt"
  },
  "scp049breathing": {
    "subtitle": "sounds.scpff.scp049breathing",
    "sounds": [
      "scpff:scp049breathing"
    ]
  },
  "scp106breathing": {
    "subtitle": "sounds.scpff.scp106breathing",
    "sounds": [
      "scpff:scp106breathing"
    ]
  }
}